polars_countvectorizer-0.1.0.dist-info/METADATA
polars_countvectorizer-0.1.0.dist-info/WHEEL
polars_countvectorizer-0.1.0.dist-info/licenses/LICENSE
polars_countvectorizer/__init__.py
polars_countvectorizer/polars_countvectorizer.cpython-311-darwin.so
polars_countvectorizer-0.1.0.dist-info/RECORD
