Metadata-Version: 2.3
Name: polars-countvectorizer
Version: 0.1.0
Requires-Dist: cargo >=0.3
Requires-Dist: pip >=24.3.1
License-File: LICENSE
Summary: Rust-based Python library that provides text vectorization and cosine distance calculation, optimized for use with Polars DataFrames.
Requires-Python: >=3.11
